setup.py
PyAstroChem/__init__.py
PyAstroChem/chemistry.py
PyAstroChem/cooling.py
PyAstroChem/equilibrium.py
PyAstroChem/heating.py
PyAstroChem/radex.py
PyAstroChem.egg-info/PKG-INFO
PyAstroChem.egg-info/SOURCES.txt
PyAstroChem.egg-info/dependency_links.txt
PyAstroChem.egg-info/top_level.txt